README.md
setup.py
nertk/__init__.py
nertk/annotator.py
nertk.egg-info/PKG-INFO
nertk.egg-info/SOURCES.txt
nertk.egg-info/dependency_links.txt
nertk.egg-info/not-zip-safe
nertk.egg-info/requires.txt
nertk.egg-info/top_level.txt