Metadata-Version: 2.1
Name: nertk
Version: 0.0.2
Summary: Name Entity Recognition toolkit - Annotate name entities in text inline within your Jupyter notebook
Home-page: http://github.com/johnsmithm/nertk
Author: Ion Mosnoi
Author-email: moshnoi2000@gmail.com
License: MIT
Platform: UNKNOWN
